text_extensions_for_pandas/__init__.py
text_extensions_for_pandas/test_util.py
text_extensions_for_pandas/util.py
text_extensions_for_pandas/array/__init__.py
text_extensions_for_pandas/array/accessor.py
text_extensions_for_pandas/array/arrow_conversion.py
text_extensions_for_pandas/array/span.py
text_extensions_for_pandas/array/string_table.py
text_extensions_for_pandas/array/tensor.py
text_extensions_for_pandas/array/test_arrow_conversion.py
text_extensions_for_pandas/array/test_span.py
text_extensions_for_pandas/array/test_tensor.py
text_extensions_for_pandas/array/test_token_span.py
text_extensions_for_pandas/array/thing_table.py
text_extensions_for_pandas/array/token_span.py
text_extensions_for_pandas/array/token_table.py
text_extensions_for_pandas/cleaning/__init__.py
text_extensions_for_pandas/cleaning/analysis.py
text_extensions_for_pandas/cleaning/ensemble.py
text_extensions_for_pandas/cleaning/preprocess.py
text_extensions_for_pandas/io/__init__.py
text_extensions_for_pandas/io/bert.py
text_extensions_for_pandas/io/conll.py
text_extensions_for_pandas/io/spacy.py
text_extensions_for_pandas/io/test_bert.py
text_extensions_for_pandas/io/test_conll.py
text_extensions_for_pandas/io/test_spacy.py
text_extensions_for_pandas/io/watson/__init__.py
text_extensions_for_pandas/io/watson/nlu.py
text_extensions_for_pandas/io/watson/tables.py
text_extensions_for_pandas/io/watson/test_nlu.py
text_extensions_for_pandas/io/watson/test_tables.py
text_extensions_for_pandas/io/watson/util.py
text_extensions_for_pandas/jupyter/__init__.py
text_extensions_for_pandas/jupyter/misc.py
text_extensions_for_pandas/jupyter/span.py
text_extensions_for_pandas/jupyter/test_jupyter.py
text_extensions_for_pandas/jupyter/widget/__init__.py
text_extensions_for_pandas/jupyter/widget/core.py
text_extensions_for_pandas/jupyter/widget/span.py
text_extensions_for_pandas/jupyter/widget/stubs.py
text_extensions_for_pandas/jupyter/widget/table.py
text_extensions_for_pandas/resources/__init__.py
text_extensions_for_pandas-0.2.1.dist-info/LICENSE.txt
text_extensions_for_pandas-0.2.1.dist-info/METADATA
text_extensions_for_pandas-0.2.1.dist-info/WHEEL
text_extensions_for_pandas-0.2.1.dist-info/top_level.txt
text_extensions_for_pandas-0.2.1.dist-info/RECORD
