Metadata-Version: 2.1
Name: text-extensions-for-pandas
Version: 0.2.1
Summary: Natural language processing support for Pandas dataframes.
Home-page: https://github.com/CODAIT/text-extensions-for-pandas
Author: IBM
Author-email: frreiss@us.ibm.com
Classifier: Programming Language :: Python :: 3
Classifier: License :: OSI Approved :: Apache Software License
Classifier: Operating System :: OS Independent
Classifier: Topic :: Scientific/Engineering
Requires-Python: >=3.7
License-File: LICENSE.txt
Requires-Dist: numpy (>=1.20.3)
Requires-Dist: pandas (>=1.0.3)
Requires-Dist: pyarrow (>=1.0.0)
Requires-Dist: regex
Requires-Dist: importlib-resources
Requires-Dist: memoized-property
Requires-Dist: requests
Requires-Dist: packaging
